luziapi/__init__.py
luziapi/core.py
luziapi-0.1.0.dist-info/METADATA
luziapi-0.1.0.dist-info/WHEEL
luziapi-0.1.0.dist-info/top_level.txt
luziapi-0.1.0.dist-info/RECORD
