Metadata-Version: 2.2
Name: luziapi
Version: 0.1.0
Summary: Luzi API - Geliştiriciler için araçlar
Home-page: https://github.com/luzih/luziapi
Author: luzi inc
Author-email: help@luzitool.ct.ws
Classifier: Programming Language :: Python :: 3
Classifier: License :: OSI Approved :: MIT License
Classifier: Operating System :: OS Independent
Requires-Python: >=3.7
Dynamic: author
Dynamic: author-email
Dynamic: classifier
Dynamic: description
Dynamic: description-content-type
Dynamic: home-page
Dynamic: requires-python
Dynamic: summary
